mmp/__init__.py
mmp/cli/__init__.py
mmp/cli/colors.py
mmp/cli/docopt_command.py
mmp/cli/formatter.py
mmp/cli/main.py
mmp/cli/mex.py
mmp/cli/run_scripts.py
mmp/cli/signals.py
mmp/cli/utils.py
mmp/cli/errors/__init__.py
mmp/cli/errors/missing.py
mmp-0.2.1.dist-info/LICENSE
mmp-0.2.1.dist-info/METADATA
mmp-0.2.1.dist-info/WHEEL
mmp-0.2.1.dist-info/entry_points.txt
mmp-0.2.1.dist-info/top_level.txt
mmp-0.2.1.dist-info/RECORD
