Metadata-Version: 2.1
Name: mmp
Version: 0.2.1
Summary: mmp handle your py_modules easier and faster
Home-page: https://github.com/alfonsocv12/mmp
Author: Alfonso Villaobos
Author-email: alfonso@codepeat.com
License: MIT
Classifier: Development Status :: 3 - Alpha
Classifier: Programming Language :: Python :: 3.7
Classifier: License :: OSI Approved :: MIT License
Classifier: Operating System :: OS Independent
License-File: LICENSE
Requires-Dist: virtualenv >=20.4.4
Requires-Dist: docopt ==0.6.2
